pyiptables/__init__.py
pyiptables/securitygroup.py
pyiptables-2.0.7.dist-info/METADATA
pyiptables-2.0.7.dist-info/WHEEL
pyiptables-2.0.7.dist-info/top_level.txt
pyiptables-2.0.7.dist-info/RECORD
