Metadata-Version: 2.1
Name: pyiptables
Version: 2.0.7
Summary: Simple Python client library for Iptables
Home-page: https://github.com/xizhendu/pyiptables
Author: Xizhen Du
Author-email: xizhendu@gmail.com
